live_gpio/__init__.py
live_gpio/app.py
live_gpio/templates/favorites.html
live_gpio/templates/favorites_.html
live_gpio/templates/index.html
live_gpio/templates/index_.html
live_gpio/templates/pin_modes.html
live_gpio-3.0.dist-info/METADATA
live_gpio-3.0.dist-info/WHEEL
live_gpio-3.0.dist-info/entry_points.txt
live_gpio-3.0.dist-info/top_level.txt
live_gpio-3.0.dist-info/RECORD
