Metadata-Version: 2.1
Name: live-gpio
Version: 3.0
Summary: UNKNOWN
Home-page: UNKNOWN
License: UNKNOWN
Platform: UNKNOWN
Requires-Dist: Flask
Requires-Dist: Flask-SocketIO
Requires-Dist: pigpio
